django_modelforms-0.3.0.dist-info/DESCRIPTION.rst
django_modelforms-0.3.0.dist-info/METADATA
django_modelforms-0.3.0.dist-info/RECORD
django_modelforms-0.3.0.dist-info/WHEEL
django_modelforms-0.3.0.dist-info/metadata.json
django_modelforms-0.3.0.dist-info/top_level.txt
modelforms/__init__.py
modelforms/forms.py
modelforms/mixins.py
modelforms/views.py
tests/__init__.py
tests/models.py
tests/settings.py
tests/tests.py
tests/urls.py
tests/views.py
tests/wsgi.py
