Metadata-Version: 2.0
Name: django-modelforms
Version: 0.3.0
Summary: Improvements to django.forms.ModelForm
Home-page: UNKNOWN
Author: Touch Technology Pty Ltd
Author-email: info@touchtechnology.com.au
Maintainer: Gary Reynolds
Maintainer-email: gary.reynolds@touchtechnology.com.au
License: BSD
Platform: UNKNOWN
Requires-Dist: django
